{
    "it": {
        "words": [
            "adesso",
            "allora",
            "anche",
            "ancora",
            "certo",
            "che",
            "ci",
            "come",
            "quando",
            "perché",
            "quale",
            "quanto",
            "quasi",
            "solo",
            "sempre",
            "senza",
            "sopra",
            "sotto",
            "tutto",
            "una",
            "uno",
            "vedere",
            "volere",
            "a",
            "ad",
            "al",
            "alla",
            "alle",
            "anche",
            "ci",
            "che",
            "con",
            "da",
            "del",
            "dei",
            "delle",
            "di",
            "dopo",
            "ecco",
            "ed",
            "essere",
            "ha",
            "in",
            "ma",
            "mi",
            "nel",
            "ne",
            "no",
            "noi",
            "non",
            "o",
            "per",
            "piu",
            "quasi",
            "se",
            "si",
            "sul",
            "sui",
            "sulle",
            "sulla",
            "tra",
            "tu",
            "un",
            "una",
            "uno",
            "verso",
            "vi",
            "voi"
        ],
        "articles": [
            "il",
            "lo",
            "la",
            "i",
            "gli",
            "le",
            "un",
            "una"
        ]
    },
    "en": {
        "words": [
            "and",
            "are",
            "as",
            "at",
            "be",
            "by",
            "for",
            "from",
            "has",
            "he",
            "in",
            "is",
            "it",
            "its",
            "of",
            "on",
            "that",
            "to",
            "was",
            "were",
            "with",
            "all",
            "any",
            "both",
            "but",
            "can",
            "do",
            "every",
            "few",
            "had",
            "her",
            "him",
            "his",
            "how",
            "I",
            "if",
            "into",
            "like",
            "me",
            "more",
            "my",
            "no",
            "not",
            "now",
            "or",
            "our",
            "out",
            "some",
            "so",
            "than",
            "their",
            "them",
            "then",
            "there",
            "these",
            "they",
            "this",
            "us",
            "we",
            "what",
            "when",
            "where",
            "which",
            "who",
            "why",
            "will",
            "you",
            "your"
        ],
        "articles": [
            "the",
            "a",
            "an"
        ]
    }
}